LICENSE
MANIFEST.in
README.md
helga_hipster.py
setup.py
helga_hipster.egg-info/PKG-INFO
helga_hipster.egg-info/SOURCES.txt
helga_hipster.egg-info/dependency_links.txt
helga_hipster.egg-info/entry_points.txt
helga_hipster.egg-info/requires.txt
helga_hipster.egg-info/top_level.txt